ServeExl.py
tnsname_formatter-0.1.0.dist-info/METADATA
tnsname_formatter-0.1.0.dist-info/WHEEL
tnsname_formatter-0.1.0.dist-info/top_level.txt
tnsname_formatter-0.1.0.dist-info/RECORD
