Metadata-Version: 2.1
Name: tnsname-formatter
Version: 0.1.0
Summary: A tool to format TNSnames files and download them as Excel files containing Server name and Database name
Author: Tarun Kesavan Menon
Author-email: tarunmenon383@example.com
Requires-Dist: pandas
Requires-Dist: openpyxl
